subnet_calculator_mcp/__init__.py
subnet_calculator_mcp/calculators.py
subnet_calculator_mcp/server.py
subnet_calculator_mcp/tools.py
subnet_calculator_mcp/validators.py
subnet_calculator_mcp/world_model.py
subnet_calculator_mcp-0.1.3.dist-info/METADATA
subnet_calculator_mcp-0.1.3.dist-info/WHEEL
subnet_calculator_mcp-0.1.3.dist-info/entry_points.txt
subnet_calculator_mcp-0.1.3.dist-info/licenses/LICENSE
subnet_calculator_mcp-0.1.3.dist-info/RECORD
