Metadata-Version: 2.4
Name: subnet-calculator-mcp
Version: 0.1.3
Summary: IPv4 subnet calculator MCP server for host planning, wildcard masks, and IP validation
Project-URL: Homepage, https://github.com/sanjayshreeyans/subnet-calculator-mcp
Project-URL: Documentation, https://github.com/sanjayshreeyans/subnet-calculator-mcp#readme
Project-URL: Repository, https://github.com/sanjayshreeyans/subnet-calculator-mcp
Project-URL: Issues, https://github.com/sanjayshreeyans/subnet-calculator-mcp/issues
Author-email: Sanjay Shreeyans Javangula <sanjayshreeyans@gmail.com>
License: MIT
License-File: LICENSE
Keywords: calculator,cisco,mcp,networking,ospf,subnet
Classifier: Development Status :: 4 - Beta
Classifier: Intended Audience :: Developers
Classifier: Intended Audience :: System Administrators
Classifier: License :: OSI Approved :: MIT License
Classifier: Programming Language :: Python :: 3
Classifier: Programming Language :: Python :: 3.10
Classifier: Programming Language :: Python :: 3.11
Classifier: Programming Language :: Python :: 3.12
Classifier: Topic :: Software Development :: Libraries :: Python Modules
Classifier: Topic :: System :: Networking
Requires-Python: >=3.10
Requires-Dist: mcp>=1.4.0
Requires-Dist: networkx>=3.0
Requires-Dist: pydantic>=2.0.0
Provides-Extra: dev
Requires-Dist: black>=23.0.0; extra == 'dev'
Requires-Dist: mypy>=1.0.0; extra == 'dev'
Requires-Dist: pytest-asyncio>=0.21.0; extra == 'dev'
Requires-Dist: pytest>=7.0.0; extra == 'dev'
Requires-Dist: ruff>=0.1.0; extra == 'dev'
Requires-Dist: types-networkx>=3.0.0; extra == 'dev'
